spectra_dio/__init__.py
spectra_dio/config.py
spectra_dio/ftsio_dio.py
spectra_dio-1.0.0.dist-info/METADATA
spectra_dio-1.0.0.dist-info/WHEEL
spectra_dio-1.0.0.dist-info/licenses/LICENSE
spectra_dio-1.0.0.dist-info/RECORD
